<?xml version="1.0" encoding="UTF-8"?><?xml-stylesheet type='text/xsl' href='./CodelistDictionary-v32.xsl'?><Dictionary xmlns="http://www.opengis.net/gml/3.2" xmlns:gml="http://www.opengis.net/gml/3.2" xmlns:xsi="http://www.w3.org/2001/XMLSchema-instance" gml:id="FormOfWaterwayNodeValue" xsi:schemaLocation="http://www.opengis.net/gml/3.2 http://schemas.opengis.net/gml/3.2.1/gml.xsd">
  <description>-- Definition --&#13;
Function of a WaterwayNode in the water transport network.</description>
  <identifier codeSpace="urn:x-inspire:specification:gmlas:WaterTransportNetwork:3.0">FormOfWaterwayNodeValue</identifier>
  <dictionaryEntry>
    <Definition gml:id="_21909_37585">
      <description>-- Definition --&#13;
Infrastructure elements where the one vessel traffic flow crosses another vessel traffic flow or points where vessel traffic flows divide or come together.&#13;
&#13;
-- Description --&#13;
SOURCE [COMPRIS].&#13;
</description>
      <identifier codeSpace="urn:x-inspire:specification:gmlas:WaterTransportNetwork:3.0/FormOfWaterwayNodeValue">junctionFork</identifier>
      <name>junctionFork</name>
    </Definition>
  </dictionaryEntry>
  <dictionaryEntry>
    <Definition gml:id="_21909_37586">
      <description>-- Definition --&#13;
Lock or group of locks, intended for raising and lowering boats between stretches of water of different levels on river and canal waterways.</description>
      <identifier codeSpace="urn:x-inspire:specification:gmlas:WaterTransportNetwork:3.0/FormOfWaterwayNodeValue">lockComplex</identifier>
      <name>lockComplex</name>
    </Definition>
  </dictionaryEntry>
  <dictionaryEntry>
    <Definition gml:id="_21909_37587">
      <description>-- Definition --&#13;
Bridge that can be raised or turned to allow the passage of ships.</description>
      <identifier codeSpace="urn:x-inspire:specification:gmlas:WaterTransportNetwork:3.0/FormOfWaterwayNodeValue">movableBridge</identifier>
      <name>movableBridge</name>
    </Definition>
  </dictionaryEntry>
  <dictionaryEntry>
    <Definition gml:id="_21909_37588">
      <description>-- Definition --&#13;
The location where goods are transhipped. &#13;
&#13;
-- Description --&#13;
SOURCE [COMPRIS].&#13;
&#13;
NOTE A terminal forms a link between the various transport modes, of which shipping is one. A terminal therefore has waterside loading and unloading places [COMPRIS].&#13;
</description>
      <identifier codeSpace="urn:x-inspire:specification:gmlas:WaterTransportNetwork:3.0/FormOfWaterwayNodeValue">terminal</identifier>
      <name>terminal</name>
    </Definition>
  </dictionaryEntry>
  <dictionaryEntry>
    <Definition gml:id="_21909_37589">
      <description>-- Definition --&#13;
A place where a canal or narrow waterway is widened to allow boats to turn around.</description>
      <identifier codeSpace="urn:x-inspire:specification:gmlas:WaterTransportNetwork:3.0/FormOfWaterwayNodeValue">turningBasin</identifier>
      <name>turningBasin</name>
    </Definition>
  </dictionaryEntry>
  <dictionaryEntry>
    <Definition gml:id="_21909_37590">
      <description>-- Definition --&#13;
A machine for transporting boats between water bodies at two different elevations, which is used as an alternative to the canal locks..&#13;
&#13;
-- Description --&#13;
NOTE Synonyms: boat lift, lift lock.&#13;
</description>
      <identifier codeSpace="urn:x-inspire:specification:gmlas:WaterTransportNetwork:3.0/FormOfWaterwayNodeValue">shipLift</identifier>
      <name>shipLift</name>
    </Definition>
  </dictionaryEntry>
</Dictionary>
